bom_mysql/__init__.py
bom_mysql/__main__.py
bom_mysql/base.py
bom_mysql-0.1.0.dist-info/LICENSE
bom_mysql-0.1.0.dist-info/METADATA
bom_mysql-0.1.0.dist-info/WHEEL
bom_mysql-0.1.0.dist-info/entry_points.txt
bom_mysql-0.1.0.dist-info/top_level.txt
bom_mysql-0.1.0.dist-info/RECORD
