Metadata-Version: 2.1
Name: bom-mysql
Version: 0.1.0
Summary: Awesome bom_mysql created by bommaru-com
Home-page: https://github.com/bommaru-com/bom_mysql
Author: bommaru-com
License: UNKNOWN
Platform: UNKNOWN
License-File: LICENSE
Requires-Dist: pymysql
Requires-Dist: sshtunnel
Requires-Dist: python-dotenv
Requires-Dist: loguru
Requires-Dist: backoff
Provides-Extra: test
Requires-Dist: pytest ; extra == 'test'
Requires-Dist: coverage ; extra == 'test'
Requires-Dist: flake8 ; extra == 'test'
Requires-Dist: black ; extra == 'test'
Requires-Dist: isort ; extra == 'test'
Requires-Dist: pytest-cov ; extra == 'test'
Requires-Dist: codecov ; extra == 'test'
Requires-Dist: mypy ; extra == 'test'
Requires-Dist: gitchangelog ; extra == 'test'
Requires-Dist: mkdocs ; extra == 'test'
